tokenex/__init__.py
tokenex/cli.py
tokenex/tokenex.py
tokenex/tests/__init__.py
tokenex/tests/conftest.py
tokenex/tests/test_cli.py
tokenex/tests/test_tokenex.py
python_tokenex-0.1.1.dist-info/AUTHORS
python_tokenex-0.1.1.dist-info/METADATA
python_tokenex-0.1.1.dist-info/WHEEL
python_tokenex-0.1.1.dist-info/entry_points.txt
python_tokenex-0.1.1.dist-info/pbr.json
python_tokenex-0.1.1.dist-info/top_level.txt
python_tokenex-0.1.1.dist-info/RECORD
