Metadata-Version: 2.1
Name: python-tokenex
Version: 0.1.1
Summary: Python Module and CLI for interacting with TokenEx services
Home-page: https://github.com/tablethotels/python-tokenex
Author: Tablet, Inc
Author-email: ops@tablethotels.com
License: MIT License
Classifier: Intended Audience :: Developers
Classifier: Natural Language :: English
Classifier: Programming Language :: Python
Classifier: Programming Language :: Python :: 2.7
Classifier: Programming Language :: Python :: 3.4
Classifier: Programming Language :: Python :: 3.5
Classifier: Programming Language :: Python :: 3.6
Classifier: Programming Language :: Python :: 3.7
Requires-Dist: requests
Requires-Dist: argparse
